pathfinding_challenge/__init__.py
pathfinding_challenge/algorithms/__init__.py
pathfinding_challenge/algorithms/a_star.py
pathfinding_challenge/algorithms/context.py
pathfinding_challenge/algorithms/dijkstra.py
pathfinding_challenge/algorithms/example.py
pathfinding_challenge/algorithms/path_finding.py
pathfinding_challenge/entities/__init__.py
pathfinding_challenge/entities/down_hill.py
pathfinding_challenge/entities/node.py
pathfinding_challenge/entities/plateau.py
pathfinding_challenge/entities/position.py
pathfinding_challenge/entities/up_hill.py
pathfinding_challenge/entities/valley.py
pathfinding_challenge/utils/__init__.py
pathfinding_challenge-1.0.1.dist-info/LICENSE
pathfinding_challenge-1.0.1.dist-info/METADATA
pathfinding_challenge-1.0.1.dist-info/WHEEL
pathfinding_challenge-1.0.1.dist-info/RECORD
