Metadata-Version: 2.1
Name: pathfinding_challenge
Version: 1.0.1
Summary: Fuel Efficiency Pathfinding System Challenge
Author: Lucas S. Althoff
Requires-Python: >=3.10.4,<4.0.0
Classifier: Development Status :: 5 - Production/Stable
Classifier: License :: OSI Approved :: MIT License
Classifier: Operating System :: OS Independent
Classifier: Programming Language :: Python :: 3
Classifier: Programming Language :: Python :: 3.11
Classifier: Programming Language :: Python :: 3.12
Classifier: Programming Language :: Python :: 3.10
Classifier: Topic :: Scientific/Engineering
Project-URL: Homepage, https://github.com/lucas-althoff/BeesDataChallenge_ML/
Project-URL: Issues, https://github.com/lucas-althoff/BeesDataChallenge_ML/issues
